Fumagalli_Motta_Tarantino_2020/Project.py
Fumagalli_Motta_Tarantino_2020/__init__.py
Fumagalli_Motta_Tarantino_2020/Configurations/ConfigExceptions.py
Fumagalli_Motta_Tarantino_2020/Configurations/FindConfig.py
Fumagalli_Motta_Tarantino_2020/Configurations/LoadConfig.py
Fumagalli_Motta_Tarantino_2020/Configurations/StoreConfig.py
Fumagalli_Motta_Tarantino_2020/Configurations/__init__.py
Fumagalli_Motta_Tarantino_2020/Configurations/params.csv
Fumagalli_Motta_Tarantino_2020/Models/Base.py
Fumagalli_Motta_Tarantino_2020/Models/BaseExtended.py
Fumagalli_Motta_Tarantino_2020/Models/Distributions.py
Fumagalli_Motta_Tarantino_2020/Models/Exceptions.py
Fumagalli_Motta_Tarantino_2020/Models/Extension.py
Fumagalli_Motta_Tarantino_2020/Models/Types.py
Fumagalli_Motta_Tarantino_2020/Models/__init__.py
Fumagalli_Motta_Tarantino_2020/Notebooks/Analysis.ipynb
Fumagalli_Motta_Tarantino_2020/Notebooks/Configurations.ipynb
Fumagalli_Motta_Tarantino_2020/Notebooks/Figures.ipynb
Fumagalli_Motta_Tarantino_2020/Notebooks/Interactive.ipynb
Fumagalli_Motta_Tarantino_2020/Notebooks/NotebookUtilities.py
Fumagalli_Motta_Tarantino_2020/Notebooks/Tutorial.ipynb
Fumagalli_Motta_Tarantino_2020/Notebooks/__init__.py
Fumagalli_Motta_Tarantino_2020/Tests/Mock.py
Fumagalli_Motta_Tarantino_2020/Tests/Test_Base.py
Fumagalli_Motta_Tarantino_2020/Tests/Test_BaseExtended.py
Fumagalli_Motta_Tarantino_2020/Tests/Test_Configurations.py
Fumagalli_Motta_Tarantino_2020/Tests/Test_Distributions.py
Fumagalli_Motta_Tarantino_2020/Tests/Test_Extension.py
Fumagalli_Motta_Tarantino_2020/Tests/Test_NotebookUtilities.py
Fumagalli_Motta_Tarantino_2020/Tests/Test_Types.py
Fumagalli_Motta_Tarantino_2020/Tests/Test_Visualize.py
Fumagalli_Motta_Tarantino_2020/Tests/__init__.py
Fumagalli_Motta_Tarantino_2020/Visualizations/Visualize.py
Fumagalli_Motta_Tarantino_2020/Visualizations/VisualizeRanges.py
Fumagalli_Motta_Tarantino_2020/Visualizations/__init__.py
Fumagalli_Motta_Tarantino_2020-1.0.2.dist-info/LICENSE
Fumagalli_Motta_Tarantino_2020-1.0.2.dist-info/METADATA
Fumagalli_Motta_Tarantino_2020-1.0.2.dist-info/WHEEL
Fumagalli_Motta_Tarantino_2020-1.0.2.dist-info/top_level.txt
Fumagalli_Motta_Tarantino_2020-1.0.2.dist-info/RECORD
