Metadata-Version: 2.1
Name: Fumagalli_Motta_Tarantino_2020
Version: 1.0.2
Summary: Implements the models presented in Fumagalli et al. (2020)
Home-page: https://github.com/manuelbieri/Fumagalli_2020#readme
Download-URL: https://github.com/manuelbieri/Fumagalli_2020/archive/refs/tags/v1.0.2.tar.gz
Author: Manuel Bieri
Author-email: mail@manuelbieri.ch
License: MIT
Project-URL: Documentation, https://manuelbieri.ch/Fumagalli_2020/
Project-URL: Download, https://github.com/manuelbieri/Fumagalli_2020/releases
Project-URL: Source, https://github.com/manuelbieri/Fumagalli_2020
Keywords: Killer Acquisition,Competition,Innovation
Classifier: Development Status :: 5 - Production/Stable
Classifier: Intended Audience :: Developers
Classifier: Topic :: Software Development
Classifier: License :: OSI Approved :: MIT License
Classifier: Programming Language :: Python :: 3.12
License-File: LICENSE
Requires-Dist: scipy >=1.14.1
Requires-Dist: matplotlib >=3.9.2
Requires-Dist: numpy >=2.1.1
Requires-Dist: ipython >=8.27.0
Requires-Dist: jupyter ~=1.1.1
Requires-Dist: mockito ~=1.5.1
Requires-Dist: ipympl ==0.9.4
Provides-Extra: black
Requires-Dist: black >=24.8.0 ; extra == 'black'
Requires-Dist: jupyter-black >=0.4.0 ; extra == 'black'
Provides-Extra: docs
Requires-Dist: pdoc ~=14.7.0 ; extra == 'docs'
Provides-Extra: interactive
Requires-Dist: ipywidgets >=7.8.4 ; extra == 'interactive'
Provides-Extra: style
Requires-Dist: SciencePlots >=1.0.9 ; extra == 'style'
